nebari_jupyterhub_theme/__init__.py
nebari_jupyterhub_theme/custom/css/AtkinsonHyperlegible-Bold.ttf
nebari_jupyterhub_theme/custom/css/AtkinsonHyperlegible-Regular.ttf
nebari_jupyterhub_theme/custom/css/Poppins-Bold.ttf
nebari_jupyterhub_theme/custom/css/Poppins-Regular.ttf
nebari_jupyterhub_theme/custom/images/Nebari-Logo-Horizontal-Lockup-White-text.svg
nebari_jupyterhub_theme/custom/images/Nebari-logo-square.svg
nebari_jupyterhub_theme/templates/login.html
nebari_jupyterhub_theme/templates/page.html
nebari_jupyterhub_theme/templates/style.css
nebari_jupyterhub_theme-2024.7.1.dist-info/METADATA
nebari_jupyterhub_theme-2024.7.1.dist-info/WHEEL
nebari_jupyterhub_theme-2024.7.1.dist-info/licenses/LICENSE
nebari_jupyterhub_theme-2024.7.1.dist-info/RECORD
