Metadata-Version: 2.3
Name: nebari-jupyterhub-theme
Version: 2024.7.1
Summary: Nebari JupyterHub theme
Project-URL: Bug Reports, https://github.com/nebari-dev/nebari-jupyterhub-theme/issues
Project-URL: Homepage, https://nebari.dev
Project-URL: Source code, https://github.com/nebari-dev/nebari-jupyterhub-theme
Maintainer: Nebari development team
License-Expression: BSD-3-Clause
License-File: LICENSE
Keywords: jupyterhub,theme
Classifier: Development Status :: 3 - Alpha
Classifier: Intended Audience :: Developers
Classifier: Operating System :: OS Independent
Classifier: Programming Language :: Python :: 3
Classifier: Programming Language :: Python :: 3.8
Classifier: Topic :: Software Development :: Build Tools
Requires-Python: >=3.8
Requires-Dist: jupyterhub>=5.0.0
